{
    "version": "20211111",
    "description": "OpenCore Auxiliary Tools OpenCore Configurator OCAT",
    "homepage": "https://github.com/ic005k/QtOpenCoreConfig",
    "license": "Public Domain",
    "url": "https://github.com/ic005k/QtOpenCoreConfig/releases/download/20211111/OCAT-Win64.zip",
    "hash": "af1377a229335acd7b8195b31f73d7d8a738a53713e2fde19f08e215fcaec0c3",
    "extract_dir": "OCAT-Win64",
    "bin": [
        "OCAuxiliaryTools.exe",
        "Database/win/FindESP.exe",
        "Database/win/macserial.exe",
        "Database/win/ocpasswordgen.exe",
        "Database/win/ocvalidate.exe",
        "Database/win/Winfile.exe"
    ],
    "shortcuts": [
        [
            "OCAuxiliaryTools.exe",
            "OCAuxiliaryTools"
        ]
    ],
    "checkver": "github",
    "autoupdate": {
        "url": "https://github.com/ic005k/QtOpenCoreConfig/releases/download/$version/OCAT-Win64.zip",
        "extract_dir": "OCAT-Win64"
    }
}
