{
    "version": "20211018",
    "description": "OpenCore Auxiliary Tools OpenCore Configurator OCAT",
    "homepage": "https://github.com/ic005k/QtOpenCoreConfig",
    "license": "Public Domain",
    "url": "https://github.com/ic005k/QtOpenCoreConfig/releases/download/20211018/OCAT-Win64.zip",
    "hash": "03b9ec8ab35a2ff284e050f167137377979b4b2f4308f4492f97e85c46c39439",
    "extract_dir": "OCAT-Win64",
    "bin": [
        "OCAuxiliaryTools.exe",
        "Database/win/FindESP.exe",
        "Database/win/macserial.exe",
        "Database/win/ocpasswordgen.exe",
        "Database/win/ocvalidate.exe",
        "Database/win/Winfile.exe"
    ],
    "shortcuts": [
        [
            "OCAuxiliaryTools.exe",
            "OCAuxiliaryTools"
        ]
    ],
    "checkver": "github",
    "autoupdate": {
        "url": "https://github.com/ic005k/QtOpenCoreConfig/releases/download/$version/OCAT-Win64.zip",
        "extract_dir": "OCAT-Win64"
    }
}
