{
    "homepage": "https://direnv.net",
    "description": "Environment switcher for the shell",
    "license": "MIT",
    "version": "2.20.0",
    "architecture": {
        "32bit": {
            "url": "https://github.com/direnv/direnv/releases/download/v2.20.0/direnv.windows-386.exe",
            "hash": "1fe776c1e0dd5d4af2af1b7418dd7f946b731d9fe2932f16c0cbda29381ccba3",
            "bin": [
                [
                    "direnv.windows-386.exe",
                    "direnv"
                ]
            ]
        },
        "64bit": {
            "url": "https://github.com/direnv/direnv/releases/download/v2.20.0/direnv.windows-amd64.exe",
            "hash": "4a17d21b409f0e82dac61107b3785924e5dfd2ed35578705205af5ec170372ca",
            "bin": [
                [
                    "direnv.windows-amd64.exe",
                    "direnv"
                ]
            ]
        }
    },
    "checkver": {
        "github": "https://github.com/direnv/direnv"
    },
    "autoupdate": {
        "architecture": {
            "32bit": {
                "url": "https://github.com/direnv/direnv/releases/download/v$version/direnv.windows-386.exe"
            },
            "64bit": {
                "url": "https://github.com/direnv/direnv/releases/download/v$version/direnv.windows-amd64.exe"
            }
        }
    }
}
